jkr/__init__.py
jkr/jkr.py
jkr-1.9.dist-info/METADATA
jkr-1.9.dist-info/WHEEL
jkr-1.9.dist-info/top_level.txt
jkr-1.9.dist-info/RECORD
